spcm_core/__init__.py
spcm_core/_version.py
spcm_core/constants.py
spcm_core/pyspcm.py
spcm_core/regs.py
spcm_core/spcerr.py
spcm_core/spcm_tools.py
spcm_core-1.0.8.dist-info/licenses/LICENSE
spcm_core-1.0.8.dist-info/METADATA
spcm_core-1.0.8.dist-info/WHEEL
spcm_core-1.0.8.dist-info/top_level.txt
spcm_core-1.0.8.dist-info/RECORD
