Metadata-Version: 2.4
Name: spcm_core
Version: 1.0.8
Summary: Low-level Python API Package for Spectrum Instrumentation GmbH cards
Author-email: Spectrum Instrumentation GmbH <info@spec.de>
Project-URL: Homepage, https://spectrum-instrumentation.com/
Project-URL: API, https://spectruminstrumentation.github.io/spcm-core/spcm_core.html
Project-URL: Repository, https://github.com/SpectrumInstrumentation/spcm-core
Project-URL: Examples, https://github.com/SpectrumInstrumentation/spcm-core/tree/master/src/examples
Project-URL: Knowledge Base, https://spectrum-instrumentation.com/support/knowledgebase/index.php
Classifier: Development Status :: 4 - Beta
Classifier: Intended Audience :: Developers
Classifier: Intended Audience :: Science/Research
Classifier: License :: OSI Approved :: MIT License
Classifier: Natural Language :: English
Classifier: Operating System :: POSIX :: Linux
Classifier: Operating System :: Microsoft :: Windows
Classifier: Programming Language :: Python
Classifier: Programming Language :: Python :: 2.6
Classifier: Programming Language :: Python :: 2.7
Classifier: Programming Language :: Python :: 3.6
Classifier: Programming Language :: Python :: 3.7
Classifier: Programming Language :: Python :: 3.8
Classifier: Programming Language :: Python :: 3.9
Classifier: Programming Language :: Python :: 3.10
Classifier: Programming Language :: Python :: 3.11
Classifier: Programming Language :: Python :: 3.12
Classifier: Programming Language :: Python :: 3.13
Classifier: Topic :: Scientific/Engineering
Classifier: Topic :: System :: Hardware
Requires-Python: >=2.6
License-File: LICENSE
Dynamic: license-file
